LICENSE.md
README.md
setup.py
autovideo/__init__.py
autovideo/entry_points.ini
autovideo.egg-info/PKG-INFO
autovideo.egg-info/SOURCES.txt
autovideo.egg-info/dependency_links.txt
autovideo.egg-info/entry_points.txt
autovideo.egg-info/requires.txt
autovideo.egg-info/top_level.txt
autovideo/augmentation/__init__.py
autovideo/base/__init__.py
autovideo/base/augmentation_base.py
autovideo/base/multi_augmentation_base.py
autovideo/base/supervised_base.py
autovideo/base/transformation_base.py
autovideo/common/__init__.py
autovideo/common/column_parser.py
autovideo/common/construct_predictions.py
autovideo/common/dataset_to_dataframe.py
autovideo/common/dataset_utils.py
autovideo/common/denormalize.py
autovideo/common/extract_columns_semantic_types.py
autovideo/common/frame_extraction.py
autovideo/common/numpy_loader.py
autovideo/common/utils.py
autovideo/recognition/__init__.py
autovideo/recognition/c3d_primitive.py
autovideo/recognition/eco_full_primitive.py
autovideo/recognition/eco_primitive.py
autovideo/recognition/i3d_primitive.py
autovideo/recognition/r2p1d_primitive.py
autovideo/recognition/r3d_primitive.py
autovideo/recognition/stgcn_primitive.py
autovideo/recognition/tsm_primitive.py
autovideo/recognition/tsn_primitive.py
autovideo/recognition/R2p1D/__init__.py
autovideo/recognition/R2p1D/mean.py
autovideo/recognition/R2p1D/model.py
autovideo/recognition/R2p1D/opts.py
autovideo/recognition/R2p1D/utils.py
autovideo/recognition/R2p1D/models/__init__.py
autovideo/recognition/R2p1D/models/densenet.py
autovideo/recognition/R2p1D/models/pre_act_resnet.py
autovideo/recognition/R2p1D/models/resnet.py
autovideo/recognition/R2p1D/models/resnet2p1d.py
autovideo/recognition/R2p1D/models/resnext.py
autovideo/recognition/R2p1D/models/wide_resnet.py
autovideo/recognition/eco_utils/__init__.py
autovideo/recognition/eco_utils/eco/__init__.py
autovideo/recognition/eco_utils/eco/layer_factory.py
autovideo/recognition/eco_utils/eco/pytorch_load.py
autovideo/recognition/eco_utils/eco_full/__init__.py
autovideo/recognition/eco_utils/eco_full/layer_factory.py
autovideo/recognition/eco_utils/eco_full/pytorch_load.py
autovideo/searcher/__init__.py
autovideo/searcher/base.py
