Metadata-Version: 2.1
Name: autovideo
Version: 1.2.2
Summary: An Automated Video Action Recognition System
Home-page: https://github.com/datamllab/autovideo
Author: DATA Lab
License: UNKNOWN
Platform: UNKNOWN
Classifier: Programming Language :: Python :: 3.6
Classifier: Programming Language :: Python :: 3.7
Classifier: Programming Language :: Python :: 3.8
Classifier: Programming Language :: Python :: 3.9
Classifier: License :: OSI Approved :: MIT License
Classifier: Operating System :: OS Independent
License-File: LICENSE.md
